phoneNum/__init__.py
phoneNum/phoneNum.py
phoneNum-0.2.dist-info/LICENSE
phoneNum-0.2.dist-info/METADATA
phoneNum-0.2.dist-info/WHEEL
phoneNum-0.2.dist-info/entry_points.txt
phoneNum-0.2.dist-info/top_level.txt
phoneNum-0.2.dist-info/RECORD
