Metadata-Version: 2.1
Name: phoneNum
Version: 0.2
Summary: get company information with phone number
Home-page: UNKNOWN
Author: Anning Chen
Author-email: anchen@milie.co.jp
License: UNKNOWN
Platform: UNKNOWN
Classifier: Programming Language :: Python :: 3
Classifier: License :: OSI Approved :: MIT License
Classifier: Operating System :: OS Independent
